servir_template.py
app/__init__.py
app/__main__.py
app/application.py
default_files/__init__.py
default_files/settings.py
default_files/urls.py
servir_template/__init__.py
servir_template/servir_template.py
servir_template/app/__init__.py
servir_template/app/__main__.py
servir_template/app/application.py
servir_template/default_files/__init__.py
servir_template/default_files/settings.py
servir_template/default_files/urls.py
servir_template/support/.gitignore
servir_template/support/.jshintrc
servir_template/support/README.md
servir_template/support/data.json
servir_template/support/environment.yml
servir_template/support/license
servir_template/support/main
servir_template/support/SERVIR_AppTemplate/settings.py
servir_template/support/SERVIR_AppTemplate/urls.py
servir_template/support/WebApp/__init__.py
servir_template/support/WebApp/admin.py
servir_template/support/WebApp/api_handlers.py
servir_template/support/WebApp/apps.py
servir_template/support/WebApp/forms.py
servir_template/support/WebApp/models.py
servir_template/support/WebApp/tests.py
servir_template/support/WebApp/urls.py
servir_template/support/WebApp/utils.py
servir_template/support/WebApp/views.py
servir_template/support/WebApp/migrations/0001_initial.py
servir_template/support/WebApp/migrations/0002_alter_station_station_elev_and_more.py
servir_template/support/WebApp/migrations/0003_alter_measurement_measurement_date.py
servir_template/support/WebApp/migrations/__init__.py
servir_template/support/WebApp/static/css/L.Control.Opacity.css
servir_template/support/WebApp/static/css/about.css
servir_template/support/WebApp/static/css/all.min.css
servir_template/support/WebApp/static/css/base.css
servir_template/support/WebApp/static/css/basic.css
servir_template/support/WebApp/static/css/chart.css
servir_template/support/WebApp/static/css/common.css
servir_template/support/WebApp/static/css/fixed_map.css
servir_template/support/WebApp/static/css/full_map.css
SERVIR_Template_CLI-0.0.40.dist-info/LICENSE
SERVIR_Template_CLI-0.0.40.dist-info/METADATA
SERVIR_Template_CLI-0.0.40.dist-info/WHEEL
SERVIR_Template_CLI-0.0.40.dist-info/entry_points.txt
SERVIR_Template_CLI-0.0.40.dist-info/top_level.txt
SERVIR_Template_CLI-0.0.40.dist-info/RECORD
