Metadata-Version: 2.1
Name: SERVIR-Template-CLI
Version: 0.0.40
Summary: Installer for the SERVIR App Template
Home-page: https://github.com/SERVIR/SERVIR_Template_CLI
Author: Billy Ashmall
Author-email: billy.ashmall@nasa.gov
License: MIT License
Classifier: Programming Language :: Python :: 3.9
Classifier: Operating System :: OS Independent
Requires-Python: >=3.9
License-File: LICENSE
Requires-Dist: click (>=7.1.2)
Requires-Dist: django (>=4.1)
Requires-Dist: gitpython
